sysdbg/__init__.py
sysdbg-1.0.0.dist-info/METADATA
sysdbg-1.0.0.dist-info/WHEEL
sysdbg-1.0.0.dist-info/top_level.txt
sysdbg-1.0.0.dist-info/RECORD
