Metadata-Version: 2.1
Name: sysdbg
Version: 1.0.0
Summary: It wil Logs system info - Parses the Prefetch files - Recieve some other System information - And Loges Running Processes
Author: MehranSpL
Author-email: 
License: MIT
Keywords: system,prefetch,log,Process,debug
Classifier: Development Status :: 5 - Production/Stable
Classifier: Intended Audience :: Education
Classifier: Operating System :: Microsoft :: Windows :: Windows 10
Classifier: License :: OSI Approved :: MIT License
Classifier: Programming Language :: Python :: 3
Requires-Dist: psutil
Requires-Dist: datetime
Requires-Dist: wmi
Requires-Dist: requests
